supermercado/__init__.py
supermercado/burntiles.py
supermercado/edge_finder.py
supermercado/super_utils.py
supermercado/uniontiles.py
supermercado/scripts/__init__.py
supermercado/scripts/cli.py
supermercado-0.4.0.dist-info/licenses/LICENSE
supermercado-0.4.0.dist-info/METADATA
supermercado-0.4.0.dist-info/WHEEL
supermercado-0.4.0.dist-info/entry_points.txt
supermercado-0.4.0.dist-info/top_level.txt
supermercado-0.4.0.dist-info/RECORD
