Metadata-Version: 2.4
Name: supermercado
Version: 0.4.0
Summary: Supercharged mercantile
Author-email: Mapbox Raster <raster@mapbox.com>
License: The MIT License (MIT)
Project-URL: Homepage, https://github.com/mapbox/supermercado
Project-URL: Source, https://github.com/mapbox/supermercado
Keywords: mapbox,mercantile,tiles
Classifier: Development Status :: 4 - Beta
Classifier: Intended Audience :: Developers
Classifier: License :: OSI Approved :: MIT License
Classifier: Programming Language :: Python
Classifier: Programming Language :: Python :: 3
Classifier: Programming Language :: Python :: 3.12
Classifier: Topic :: Software Development :: Libraries
Classifier: Topic :: Scientific/Engineering :: GIS
Requires-Python: >=3.12
License-File: LICENSE
Requires-Dist: affine
Requires-Dist: click
Requires-Dist: click-plugins
Requires-Dist: cligj
Requires-Dist: mercantile
Requires-Dist: numpy
Requires-Dist: rasterio
Provides-Extra: test
Requires-Dist: pytest>=8.2.0; extra == "test"
Requires-Dist: pytest-cov; extra == "test"
Dynamic: license-file
